writeas_anon/__init__.py
writeas_anon-0.1.0.dist-info/LICENSE.txt
writeas_anon-0.1.0.dist-info/METADATA
writeas_anon-0.1.0.dist-info/WHEEL
writeas_anon-0.1.0.dist-info/top_level.txt
writeas_anon-0.1.0.dist-info/RECORD
