Metadata-Version: 2.1
Name: writeas-anon
Version: 0.1.0
Summary: Post anonymously to write.as
Home-page: https://gitlab.com/chgrzegorz/writeas-anon
Author: Grzegorz Chilczuk
Author-email: chgrzegorz@pm.me
License: MIT
Keywords: writeas anonymous
Platform: UNKNOWN
Classifier: Development Status :: 1 - Planning
Classifier: License :: OSI Approved :: MIT License
Classifier: Programming Language :: Python :: 3.6
Classifier: Programming Language :: Python :: 3.7
Requires-Dist: requests (<3.0.0,>=2.20.1)
